datethyme/__init__.py
datethyme/__main__.py
datethyme/_datethyme.py
datethyme/_scheduling.py
datethyme/_scheduling_utils.py
datethyme/exceptions.py
datethyme/localization/en.py
datethyme/protocols.py
datethyme/utils.py
datethyme-0.4.1.dist-info/WHEEL
datethyme-0.4.1.dist-info/entry_points.txt
datethyme-0.4.1.dist-info/METADATA
datethyme-0.4.1.dist-info/RECORD
