Metadata-Version: 2.3
Name: datethyme
Version: 0.4.1
Summary: A savory approach to date and time, built on Pydantic and datetime, with an emphasis on input validation and date/time arithmetic.
Author: Isaac Riley
Author-email: Isaac Riley <yelircaasi@proton.me>
Requires-Dist: pydantic>=2.11
Requires-Dist: deal>4.24
Requires-Dist: multipledispatch>=1
Requires-Dist: loguru>=0.7.3
Requires-Python: >=3.11, <3.15
